edudata/__init__.py
edudata/synthpop.py
edudata/datasets/__init__.py
edudata/datasets/ageculture/__init__.py
edudata/datasets/ageculture/data/ageculture.csv
edudata/datasets/ageculture/data/dtypes.json
edudata/datasets/amongus/__init__.py
edudata/datasets/amongus/data/amongus.csv
edudata/datasets/amongus/data/dtypes.json
edudata/datasets/bakerysales/__init__.py
edudata/datasets/bakerysales/data/bakerysales.csv
edudata/datasets/bakerysales/data/bakerysales_eng.csv
edudata/datasets/bakerysales/data/dtypes.json
edudata/datasets/baseball/__init__.py
edudata/datasets/baseball/data/baseball.csv
edudata/datasets/baseball/data/dtypes.json
edudata/datasets/bodyperformance/__init__.py
edudata/datasets/bodyperformance/data/bodyperformance.csv
edudata/datasets/bodyperformance/data/dtypes.json
edudata/datasets/culturereview/__init__.py
edudata/datasets/culturereview/data/culturereview.csv
edudata/datasets/culturereview/data/dtypes.json
edudata/datasets/datedelivery/__init__.py
edudata/datasets/datedelivery/data/datedelivery.csv
edudata/datasets/datedelivery/data/dtypes.json
edudata/datasets/disease/__init__.py
edudata/datasets/disease/data/disease.csv
edudata/datasets/disease/data/dtypes.json
edudata/datasets/earthquake/__init__.py
edudata/datasets/earthquake/data/dtypes.json
edudata/datasets/earthquake/data/earthquake.csv
edudata/datasets/energy/__init__.py
edudata/datasets/energy/data/dtypes.json
edudata/datasets/energy/data/energy.csv
edudata/datasets/eplresults/__init__.py
edudata/datasets/eplresults/data/dtypes.json
edudata/datasets/eplresults/data/eplresults.csv
edudata/datasets/eplresults/data/eplresults_entry.csv
edudata/datasets/health/__init__.py
edudata/datasets/health/data/dtypes.json
edudata/datasets/health/data/health.csv
edudata/datasets/health/data/health_eng.csv
edudata/datasets/heroesinformation/__init__.py
edudata/datasets/heroesinformation/data/dtypes.json
edudata/datasets/heroesinformation/data/heroesinformation.csv
edudata/datasets/lolgame/__init__.py
edudata4ai-1.1.5.dist-info/licenses/LICENSE
edudata4ai-1.1.5.dist-info/METADATA
edudata4ai-1.1.5.dist-info/WHEEL
edudata4ai-1.1.5.dist-info/top_level.txt
edudata4ai-1.1.5.dist-info/RECORD
